{
    "format_version": 2,
    "tooth": "CustomMob",
    "version": "2.0.0",
    "info": {
        "name": "CustomMob",
        "description": "自定义生成的生物",
        "author": "xianyubb",
        "tags": [
            "platform:levilamina",
            "type:mod"
        ]
    },
    "prerequisites": {
        "github.com/LiteLDev/LeviLamina": "1.0.0-rc.3"
    },
    "files": {
        "place": [
            {
                "src": "CustomMob/*",
                "dest": "plugins/CustomMob/"
            }
        ]
    }
}
